MANIFEST.in
l10n_et_wizard.xml
setup.py
./__init__.py
./__openerp__.py
data/account.account.template.csv
data/account.account.type.csv
data/account.chart.template.csv
data/account.tax.code.template.csv
data/account.tax.template.csv
data/res.country.state.csv
openerp_l10n_et.egg-info/PKG-INFO
openerp_l10n_et.egg-info/SOURCES.txt
openerp_l10n_et.egg-info/dependency_links.txt
openerp_l10n_et.egg-info/requires.txt
openerp_l10n_et.egg-info/top_level.txt
static/src/img/icon.png